odoo/addons/l10n_it_account/README.rst
odoo/addons/l10n_it_account/__init__.py
odoo/addons/l10n_it_account/__manifest__.py
odoo/addons/l10n_it_account/i18n/es_AR.po
odoo/addons/l10n_it_account/i18n/it.po
odoo/addons/l10n_it_account/i18n/l10n_it_account.pot
odoo/addons/l10n_it_account/i18n/sl.po
odoo/addons/l10n_it_account/migrations/11.0.1.3.3/post-migration.py
odoo/addons/l10n_it_account/models/__init__.py
odoo/addons/l10n_it_account/models/account_account.py
odoo/addons/l10n_it_account/models/account_group.py
odoo/addons/l10n_it_account/models/account_tax.py
odoo/addons/l10n_it_account/models/account_type.py
odoo/addons/l10n_it_account/readme/CONTRIBUTORS.rst
odoo/addons/l10n_it_account/readme/CREDITS.rst
odoo/addons/l10n_it_account/readme/DESCRIPTION.rst
odoo/addons/l10n_it_account/reports/account_reports_view.xml
odoo/addons/l10n_it_account/static/description/icon.png
odoo/addons/l10n_it_account/static/description/index.html
odoo/addons/l10n_it_account/static/src/css/l10n_it_account.css
odoo/addons/l10n_it_account/tests/__init__.py
odoo/addons/l10n_it_account/tests/test_l10n_it_account.py
odoo/addons/l10n_it_account/views/account_menuitem.xml
odoo/addons/l10n_it_account/views/account_setting.xml
odoo/addons/l10n_it_account/views/account_view.xml
odoo/addons/l10n_it_account/views/partner_view.xml
odoo/addons/l10n_it_account/views/product_view.xml
odoo/addons/l10n_it_account/views/res_config_settings_views.xml
odoo11_addon_l10n_it_account-11.0.1.3.4.dist-info/METADATA
odoo11_addon_l10n_it_account-11.0.1.3.4.dist-info/WHEEL
odoo11_addon_l10n_it_account-11.0.1.3.4.dist-info/top_level.txt
odoo11_addon_l10n_it_account-11.0.1.3.4.dist-info/RECORD
