Metadata-Version: 2.1
Name: odoo11-addon-l10n-it-account
Version: 11.0.1.3.4
Summary: Italian Localization - Account
Home-page: https://github.com/OCA/l10n-italy/tree/11.0/l10n_it_account
Author: Agile Business Group, Abstract, Odoo Community Association (OCA)
Author-email: support@odoo-community.org
License: AGPL-3
Platform: UNKNOWN
Classifier: Programming Language :: Python
Classifier: Framework :: Odoo
Classifier: License :: OSI Approved :: GNU Affero General Public License v3
Requires-Python: >=2.7, !=3.0.*, !=3.1.*, !=3.2.*, !=3.3.*, !=3.4.*
Requires-Dist: odoo11-addon-account-fiscal-year
Requires-Dist: odoo11-addon-account-tax-balance
Requires-Dist: odoo (<11.1dev,>=11.0a)
